{
  "kind": "ref",
  "body_type": "[]sdk.Log",
  "body": [
    {
      "timestamp": "2025-07-14T18:35:54.463886075Z",
      "message": "Deploying nginx to staging environment",
      "attributes": {
        "col": "10",
        "filename": "./tasks.ocu.star",
        "line": "23",
        "thread": "up"
      },
      "stream": 0
    },
    {
      "timestamp": "2025-07-14T18:35:54.465969004Z",
      "message": "Installing infisical",
      "attributes": {
        "col": "14",
        "filename": "../infisical.star",
        "line": "24",
        "thread": "up"
      },
      "stream": 0
    },
    {
      "timestamp": "2025-07-14T18:35:54.468932981Z",
      "message": "/usr/bin/apt-get",
      "attributes": {
        "col": "30",
        "filename": "sdk/0.3.0/host.star",
        "line": "45",
        "thread": "up"
      },
      "stream": 0
    },
    {
      "timestamp": "2025-07-14T18:35:54.866518316Z",
      "message": "Executing the  setup script for the 'infisical/infisical-cli' repository ...",
      "attributes": {
        "col": "30",
        "filename": "sdk/0.3.0/host.star",
        "line": "45",
        "thread": "up"
      },
      "stream": 0
    },
    {
      "timestamp": "2025-07-14T18:35:54.867600803Z",
      "message": "\u001b[1K\r",
      "attributes": {
        "col": "30",
        "filename": "sdk/0.3.0/host.star",
        "line": "45",
        "thread": "up"
      },
      "stream": 0
    },
    {
      "timestamp": "2025-07-14T18:35:54.868132985Z",
      "message": "\u001b[32m  RUN\u001b[39;49m: Checking for required executable 'curl' ...",
      "attributes": {
        "col": "30",
        "filename": "sdk/0.3.0/host.star",
        "line": "45",
        "thread": "up"
      },
      "stream": 0
    },
    {
      "timestamp": "2025-07-14T18:35:54.868323145Z",
      "message": "\u001b[1K\r",
      "attributes": {
        "col": "30",
        "filename": "sdk/0.3.0/host.star",
        "line": "45",
        "thread": "up"
      },
      "stream": 0
    },
    {
      "timestamp": "2025-07-14T18:35:54.869440518Z",
      "message": "\u001b[1K\r",
      "attributes": {
        "col": "30",
        "filename": "sdk/0.3.0/host.star",
        "line": "45",
        "thread": "up"
      },
      "stream": 0
    },
    {
      "timestamp": "2025-07-14T18:35:54.870098165Z",
      "message": "\u001b[32m   OK\u001b[39;49m: Checking for required executable 'curl' ...",
      "attributes": {
        "col": "30",
        "filename": "sdk/0.3.0/host.star",
        "line": "45",
        "thread": "up"
      },
      "stream": 0
    },
    {
      "timestamp": "2025-07-14T18:35:54.871294777Z",
      "message": "\u001b[1K\r",
      "attributes": {
        "col": "30",
        "filename": "sdk/0.3.0/host.star",
        "line": "45",
        "thread": "up"
      },
      "stream": 0
    },
    {
      "timestamp": "2025-07-14T18:35:54.87184363Z",
      "message": "\u001b[32m  RUN\u001b[39;49m: Checking for required executable 'apt-get' ...",
      "attributes": {
        "col": "30",
        "filename": "sdk/0.3.0/host.star",
        "line": "45",
        "thread": "up"
      },
      "stream": 0
    },
    {
      "timestamp": "2025-07-14T18:35:54.872022954Z",
      "message": "\u001b[1K\r",
      "attributes": {
        "col": "30",
        "filename": "sdk/0.3.0/host.star",
        "line": "45",
        "thread": "up"
      },
      "stream": 0
    },
    {
      "timestamp": "2025-07-14T18:35:54.873153194Z",
      "message": "\u001b[1K\r",
      "attributes": {
        "col": "30",
        "filename": "sdk/0.3.0/host.star",
        "line": "45",
        "thread": "up"
      },
      "stream": 0
    },
    {
      "timestamp": "2025-07-14T18:35:54.873820086Z",
      "message": "\u001b[32m   OK\u001b[39;49m: Checking for required executable 'apt-get' ...",
      "attributes": {
        "col": "30",
        "filename": "sdk/0.3.0/host.star",
        "line": "45",
        "thread": "up"
      },
      "stream": 0
    },
    {
      "timestamp": "2025-07-14T18:35:54.876963872Z",
      "message": "\u001b[1K\r",
      "attributes": {
        "col": "30",
        "filename": "sdk/0.3.0/host.star",
        "line": "45",
        "thread": "up"
      },
      "stream": 0
    },
    {
      "timestamp": "2025-07-14T18:35:54.877619215Z",
      "message": "\u001b[32m  RUN\u001b[39;49m: ",
      "attributes": {
        "col": "30",
        "filename": "sdk/0.3.0/host.star",
        "line": "45",
        "thread": "up"
      },
      "stream": 0
    },
    {
      "timestamp": "2025-07-14T18:35:54.877870919Z",
      "message": "\u001b[1K\r",
      "attributes": {
        "col": "30",
        "filename": "sdk/0.3.0/host.star",
        "line": "45",
        "thread": "up"
      },
      "stream": 0
    },
    {
      "timestamp": "2025-07-14T18:35:54.878997518Z",
      "message": "\u001b[1K\r",
      "attributes": {
        "col": "30",
        "filename": "sdk/0.3.0/host.star",
        "line": "45",
        "thread": "up"
      },
      "stream": 0
    },
    {
      "timestamp": "2025-07-14T18:35:54.879699359Z",
      "message": "\u001b[32m   OK\u001b[39;49m: Detecting your OS distribution and release using system methods ...",
      "attributes": {
        "col": "30",
        "filename": "sdk/0.3.0/host.star",
        "line": "45",
        "thread": "up"
      },
      "stream": 0
    },
    {
      "timestamp": "2025-07-14T18:35:54.879877514Z",
      "message": " ^^^^: ... Detected/provided for your OS/distribution, version and architecture:",
      "attributes": {
        "col": "30",
        "filename": "sdk/0.3.0/host.star",
        "line": "45",
        "thread": "up"
      },
      "stream": 0
    },
    {
      "timestamp": "2025-07-14T18:35:54.879886491Z",
      "message": " \u003e\u003e\u003e\u003e:",
      "attributes": {
        "col": "30",
        "filename": "sdk/0.3.0/host.star",
        "line": "45",
        "thread": "up"
      },
      "stream": 0
    },
    {
      "timestamp": "2025-07-14T18:35:54.879890579Z",
      "message": " \u003e\u003e\u003e\u003e: ... distro=\u001b[32mubuntu\u001b[39;49m  version=",
      "attributes": {
        "col": "30",
        "filename": "sdk/0.3.0/host.star",
        "line": "45",
        "thread": "up"
      },
      "stream": 0
    },
    {
      "timestamp": "2025-07-14T18:35:54.879897732Z",
      "message": "\u001b[32m24.04\u001b[39;49m  ",
      "attributes": {
        "col": "30",
        "filename": "sdk/0.3.0/host.star",
        "line": "45",
        "thread": "up"
      },
      "stream": 0
    },
    {
      "timestamp": "2025-07-14T18:35:54.880143558Z",
      "message": "codename=\u001b[32mnoble\u001b[39;49m  arch=\u001b[32mx86_64\u001b[39;49m  ",
      "attributes": {
        "col": "30",
        "filename": "sdk/0.3.0/host.star",
        "line": "45",
        "thread": "up"
      },
      "stream": 0
    },
    {
      "timestamp": "2025-07-14T18:35:54.880154478Z",
      "message": " \u003e\u003e\u003e\u003e:",
      "attributes": {
        "col": "30",
        "filename": "sdk/0.3.0/host.star",
        "line": "45",
        "thread": "up"
      },
      "stream": 0
    },
    {
      "timestamp": "2025-07-14T18:35:54.881892165Z",
      "message": "\u001b[1K\r",
      "attributes": {
        "col": "30",
        "filename": "sdk/0.3.0/host.star",
        "line": "45",
        "thread": "up"
      },
      "stream": 0
    },
    {
      "timestamp": "2025-07-14T18:35:54.882426684Z",
      "message": "\u001b[32m  RUN\u001b[39;49m: Checking for apt dependency 'apt-transport-https' ...",
      "attributes": {
        "col": "30",
        "filename": "sdk/0.3.0/host.star",
        "line": "45",
        "thread": "up"
      },
      "stream": 0
    },
    {
      "timestamp": "2025-07-14T18:35:54.898702367Z",
      "message": "\u001b[1K\r",
      "attributes": {
        "col": "30",
        "filename": "sdk/0.3.0/host.star",
        "line": "45",
        "thread": "up"
      },
      "stream": 0
    },
    {
      "timestamp": "2025-07-14T18:35:54.89981986Z",
      "message": "\u001b[1K\r",
      "attributes": {
        "col": "30",
        "filename": "sdk/0.3.0/host.star",
        "line": "45",
        "thread": "up"
      },
      "stream": 0
    },
    {
      "timestamp": "2025-07-14T18:35:54.900384174Z",
      "message": "\u001b[32m   OK\u001b[39;49m: Checking for apt dependency 'apt-transport-https' ...",
      "attributes": {
        "col": "30",
        "filename": "sdk/0.3.0/host.star",
        "line": "45",
        "thread": "up"
      },
      "stream": 0
    },
    {
      "timestamp": "2025-07-14T18:35:54.901570126Z",
      "message": "\u001b[1K\r",
      "attributes": {
        "col": "30",
        "filename": "sdk/0.3.0/host.star",
        "line": "45",
        "thread": "up"
      },
      "stream": 0
    },
    {
      "timestamp": "2025-07-14T18:35:54.902124299Z",
      "message": "\u001b[32m  RUN\u001b[39;49m: Checking for apt dependency 'ca-certificates' ...",
      "attributes": {
        "col": "30",
        "filename": "sdk/0.3.0/host.star",
        "line": "45",
        "thread": "up"
      },
      "stream": 0
    },
    {
      "timestamp": "2025-07-14T18:35:54.916925099Z",
      "message": "\u001b[1K\r",
      "attributes": {
        "col": "30",
        "filename": "sdk/0.3.0/host.star",
        "line": "45",
        "thread": "up"
      },
      "stream": 0
    },
    {
      "timestamp": "2025-07-14T18:35:54.918042993Z",
      "message": "\u001b[1K\r",
      "attributes": {
        "col": "30",
        "filename": "sdk/0.3.0/host.star",
        "line": "45",
        "thread": "up"
      },
      "stream": 0
    },
    {
      "timestamp": "2025-07-14T18:35:54.918545649Z",
      "message": "\u001b[32m   OK\u001b[39;49m: Checking for apt dependency 'ca-certificates' ...",
      "attributes": {
        "col": "30",
        "filename": "sdk/0.3.0/host.star",
        "line": "45",
        "thread": "up"
      },
      "stream": 0
    },
    {
      "timestamp": "2025-07-14T18:35:54.9197581Z",
      "message": "\u001b[1K\r",
      "attributes": {
        "col": "30",
        "filename": "sdk/0.3.0/host.star",
        "line": "45",
        "thread": "up"
      },
      "stream": 0
    },
    {
      "timestamp": "2025-07-14T18:35:54.920430265Z",
      "message": "\u001b[32m  RUN\u001b[39;49m: Checking for apt dependency 'gnupg' ...",
      "attributes": {
        "col": "30",
        "filename": "sdk/0.3.0/host.star",
        "line": "45",
        "thread": "up"
      },
      "stream": 0
    },
    {
      "timestamp": "2025-07-14T18:35:54.935043954Z",
      "message": "\u001b[1K\r",
      "attributes": {
        "col": "30",
        "filename": "sdk/0.3.0/host.star",
        "line": "45",
        "thread": "up"
      },
      "stream": 0
    },
    {
      "timestamp": "2025-07-14T18:35:54.936132873Z",
      "message": "\u001b[1K\r",
      "attributes": {
        "col": "30",
        "filename": "sdk/0.3.0/host.star",
        "line": "45",
        "thread": "up"
      },
      "stream": 0
    },
    {
      "timestamp": "2025-07-14T18:35:54.936696911Z",
      "message": "\u001b[32m   OK\u001b[39;49m: Checking for apt dependency 'gnupg' ...",
      "attributes": {
        "col": "30",
        "filename": "sdk/0.3.0/host.star",
        "line": "45",
        "thread": "up"
      },
      "stream": 0
    },
    {
      "timestamp": "2025-07-14T18:35:54.937891038Z",
      "message": "\u001b[1K\r",
      "attributes": {
        "col": "30",
        "filename": "sdk/0.3.0/host.star",
        "line": "45",
        "thread": "up"
      },
      "stream": 0
    },
    {
      "timestamp": "2025-07-14T18:35:54.93841675Z",
      "message": "\u001b[32m  RUN\u001b[39;49m: Importing 'infisical/infisical-cli' repository GPG keys ...",
      "attributes": {
        "col": "30",
        "filename": "sdk/0.3.0/host.star",
        "line": "45",
        "thread": "up"
      },
      "stream": 0
    },
    {
      "timestamp": "2025-07-14T18:35:55.085734298Z",
      "message": "\u001b[1K\r",
      "attributes": {
        "col": "30",
        "filename": "sdk/0.3.0/host.star",
        "line": "45",
        "thread": "up"
      },
      "stream": 0
    },
    {
      "timestamp": "2025-07-14T18:35:55.086801173Z",
      "message": "\u001b[1K\r",
      "attributes": {
        "col": "30",
        "filename": "sdk/0.3.0/host.star",
        "line": "45",
        "thread": "up"
      },
      "stream": 0
    },
    {
      "timestamp": "2025-07-14T18:35:55.087356841Z",
      "message": "\u001b[32m   OK\u001b[39;49m: Checking for apt signed-by key support ...",
      "attributes": {
        "col": "30",
        "filename": "sdk/0.3.0/host.star",
        "line": "45",
        "thread": "up"
      },
      "stream": 0
    },
    {
      "timestamp": "2025-07-14T18:35:55.08756099Z",
      "message": "\u001b[1K\r",
      "attributes": {
        "col": "30",
        "filename": "sdk/0.3.0/host.star",
        "line": "45",
        "thread": "up"
      },
      "stream": 0
    },
    {
      "timestamp": "2025-07-14T18:35:55.088675502Z",
      "message": "\u001b[1K\r",
      "attributes": {
        "col": "30",
        "filename": "sdk/0.3.0/host.star",
        "line": "45",
        "thread": "up"
      },
      "stream": 0
    },
    {
      "timestamp": "2025-07-14T18:35:55.089179831Z",
      "message": "\u001b[32m   OK\u001b[39;49m: Importing 'infisical/infisical-cli' repository GPG keys ...",
      "attributes": {
        "col": "30",
        "filename": "sdk/0.3.0/host.star",
        "line": "45",
        "thread": "up"
      },
      "stream": 0
    },
    {
      "timestamp": "2025-07-14T18:35:55.090480155Z",
      "message": "\u001b[1K\r",
      "attributes": {
        "col": "30",
        "filename": "sdk/0.3.0/host.star",
        "line": "45",
        "thread": "up"
      },
      "stream": 0
    },
    {
      "timestamp": "2025-07-14T18:35:55.091050979Z",
      "message": "\u001b[32m  RUN\u001b[39;49m: Checking if upstream install config is OK ...",
      "attributes": {
        "col": "30",
        "filename": "sdk/0.3.0/host.star",
        "line": "45",
        "thread": "up"
      },
      "stream": 0
    },
    {
      "timestamp": "2025-07-14T18:35:55.548027138Z",
      "message": "\u001b[1K\r",
      "attributes": {
        "col": "30",
        "filename": "sdk/0.3.0/host.star",
        "line": "45",
        "thread": "up"
      },
      "stream": 0
    },
    {
      "timestamp": "2025-07-14T18:35:55.549190227Z",
      "message": "\u001b[1K\r",
      "attributes": {
        "col": "30",
        "filename": "sdk/0.3.0/host.star",
        "line": "45",
        "thread": "up"
      },
      "stream": 0
    },
    {
      "timestamp": "2025-07-14T18:35:55.549729133Z",
      "message": "\u001b[32m   OK\u001b[39;49m: Checking if upstream install config is OK ...",
      "attributes": {
        "col": "30",
        "filename": "sdk/0.3.0/host.star",
        "line": "45",
        "thread": "up"
      },
      "stream": 0
    },
    {
      "timestamp": "2025-07-14T18:35:55.550889768Z",
      "message": "\u001b[1K\r",
      "attributes": {
        "col": "30",
        "filename": "sdk/0.3.0/host.star",
        "line": "45",
        "thread": "up"
      },
      "stream": 0
    },
    {
      "timestamp": "2025-07-14T18:35:55.55138527Z",
      "message": "\u001b[32m  RUN\u001b[39;49m: Installing 'infisical/infisical-cli' repository via apt ...",
      "attributes": {
        "col": "30",
        "filename": "sdk/0.3.0/host.star",
        "line": "45",
        "thread": "up"
      },
      "stream": 0
    },
    {
      "timestamp": "2025-07-14T18:35:55.594264052Z",
      "message": "\u001b[1K\r",
      "attributes": {
        "col": "30",
        "filename": "sdk/0.3.0/host.star",
        "line": "45",
        "thread": "up"
      },
      "stream": 0
    },
    {
      "timestamp": "2025-07-14T18:35:55.595332723Z",
      "message": "\u001b[1K\r",
      "attributes": {
        "col": "30",
        "filename": "sdk/0.3.0/host.star",
        "line": "45",
        "thread": "up"
      },
      "stream": 0
    },
    {
      "timestamp": "2025-07-14T18:35:55.595862771Z",
      "message": "\u001b[32m   OK\u001b[39;49m: Installing 'infisical/infisical-cli' repository via apt ...",
      "attributes": {
        "col": "30",
        "filename": "sdk/0.3.0/host.star",
        "line": "45",
        "thread": "up"
      },
      "stream": 0
    },
    {
      "timestamp": "2025-07-14T18:35:55.598249702Z",
      "message": "\u001b[1K\r",
      "attributes": {
        "col": "30",
        "filename": "sdk/0.3.0/host.star",
        "line": "45",
        "thread": "up"
      },
      "stream": 0
    },
    {
      "timestamp": "2025-07-14T18:35:55.598774379Z",
      "message": "\u001b[32m  RUN\u001b[39;49m: Updating apt repository metadata cache ...",
      "attributes": {
        "col": "30",
        "filename": "sdk/0.3.0/host.star",
        "line": "45",
        "thread": "up"
      },
      "stream": 0
    },
    {
      "timestamp": "2025-07-14T18:36:02.887978892Z",
      "message": "\u001b[1K\r",
      "attributes": {
        "col": "30",
        "filename": "sdk/0.3.0/host.star",
        "line": "45",
        "thread": "up"
      },
      "stream": 0
    },
    {
      "timestamp": "2025-07-14T18:36:02.889174209Z",
      "message": "\u001b[1K\r",
      "attributes": {
        "col": "30",
        "filename": "sdk/0.3.0/host.star",
        "line": "45",
        "thread": "up"
      },
      "stream": 0
    },
    {
      "timestamp": "2025-07-14T18:36:02.88969076Z",
      "message": "\u001b[32m   OK\u001b[39;49m: Updating apt repository metadata cache ...",
      "attributes": {
        "col": "30",
        "filename": "sdk/0.3.0/host.star",
        "line": "45",
        "thread": "up"
      },
      "stream": 0
    },
    {
      "timestamp": "2025-07-14T18:36:02.890993204Z",
      "message": "\u001b[1K\r",
      "attributes": {
        "col": "30",
        "filename": "sdk/0.3.0/host.star",
        "line": "45",
        "thread": "up"
      },
      "stream": 0
    },
    {
      "timestamp": "2025-07-14T18:36:02.892071863Z",
      "message": "\u001b[1K\r",
      "attributes": {
        "col": "30",
        "filename": "sdk/0.3.0/host.star",
        "line": "45",
        "thread": "up"
      },
      "stream": 0
    },
    {
      "timestamp": "2025-07-14T18:36:02.892568127Z",
      "message": "\u001b[32m   OK\u001b[39;49m: The repository has been installed successfully - You're ready to rock!",
      "attributes": {
        "col": "30",
        "filename": "sdk/0.3.0/host.star",
        "line": "45",
        "thread": "up"
      },
      "stream": 0
    },
    {
      "timestamp": "2025-07-14T18:36:02.892657105Z",
      "message": "",
      "attributes": {
        "col": "30",
        "filename": "sdk/0.3.0/host.star",
        "line": "45",
        "thread": "up"
      },
      "stream": 0
    },
    {
      "timestamp": "2025-07-14T18:36:02.96221434Z",
      "message": "Get:1 file:/etc/apt/apt-mirrors.txt Mirrorlist [144 B]",
      "attributes": {
        "col": "30",
        "filename": "sdk/0.3.0/host.star",
        "line": "45",
        "thread": "up"
      },
      "stream": 0
    },
    {
      "timestamp": "2025-07-14T18:36:03.001183281Z",
      "message": "Hit:2 http://azure.archive.ubuntu.com/ubuntu noble InRelease",
      "attributes": {
        "col": "30",
        "filename": "sdk/0.3.0/host.star",
        "line": "45",
        "thread": "up"
      },
      "stream": 0
    },
    {
      "timestamp": "2025-07-14T18:36:03.003455406Z",
      "message": "Hit:3 http://azure.archive.ubuntu.com/ubuntu noble-updates InRelease",
      "attributes": {
        "col": "30",
        "filename": "sdk/0.3.0/host.star",
        "line": "45",
        "thread": "up"
      },
      "stream": 0
    },
    {
      "timestamp": "2025-07-14T18:36:03.005741398Z",
      "message": "Hit:4 http://azure.archive.ubuntu.com/ubuntu noble-backports InRelease",
      "attributes": {
        "col": "30",
        "filename": "sdk/0.3.0/host.star",
        "line": "45",
        "thread": "up"
      },
      "stream": 0
    },
    {
      "timestamp": "2025-07-14T18:36:03.006893155Z",
      "message": "Hit:5 http://azure.archive.ubuntu.com/ubuntu noble-security InRelease",
      "attributes": {
        "col": "30",
        "filename": "sdk/0.3.0/host.star",
        "line": "45",
        "thread": "up"
      },
      "stream": 0
    },
    {
      "timestamp": "2025-07-14T18:36:03.010600221Z",
      "message": "Get:6 https://dl.cloudsmith.io/public/infisical/infisical-cli/deb/ubuntu noble InRelease [4437 B]",
      "attributes": {
        "col": "30",
        "filename": "sdk/0.3.0/host.star",
        "line": "45",
        "thread": "up"
      },
      "stream": 0
    },
    {
      "timestamp": "2025-07-14T18:36:03.011346355Z",
      "message": "Hit:7 https://packages.microsoft.com/repos/azure-cli noble InRelease",
      "attributes": {
        "col": "30",
        "filename": "sdk/0.3.0/host.star",
        "line": "45",
        "thread": "up"
      },
      "stream": 0
    },
    {
      "timestamp": "2025-07-14T18:36:03.016741484Z",
      "message": "Hit:8 https://packages.microsoft.com/ubuntu/24.04/prod noble InRelease",
      "attributes": {
        "col": "30",
        "filename": "sdk/0.3.0/host.star",
        "line": "45",
        "thread": "up"
      },
      "stream": 0
    },
    {
      "timestamp": "2025-07-14T18:36:03.459200516Z",
      "message": "Fetched 4437 B in 0s (11.1 kB/s)",
      "attributes": {
        "col": "30",
        "filename": "sdk/0.3.0/host.star",
        "line": "45",
        "thread": "up"
      },
      "stream": 0
    },
    {
      "timestamp": "2025-07-14T18:36:03.459223991Z",
      "message": "Reading package lists...",
      "attributes": {
        "col": "30",
        "filename": "sdk/0.3.0/host.star",
        "line": "45",
        "thread": "up"
      },
      "stream": 0
    },
    {
      "timestamp": "2025-07-14T18:36:04.120647505Z",
      "message": "",
      "attributes": {
        "col": "30",
        "filename": "sdk/0.3.0/host.star",
        "line": "45",
        "thread": "up"
      },
      "stream": 0
    },
    {
      "timestamp": "2025-07-14T18:36:04.14174385Z",
      "message": "Reading package lists...",
      "attributes": {
        "col": "30",
        "filename": "sdk/0.3.0/host.star",
        "line": "45",
        "thread": "up"
      },
      "stream": 0
    },
    {
      "timestamp": "2025-07-14T18:36:04.151884138Z",
      "message": "",
      "attributes": {
        "col": "30",
        "filename": "sdk/0.3.0/host.star",
        "line": "45",
        "thread": "up"
      },
      "stream": 0
    },
    {
      "timestamp": "2025-07-14T18:36:04.155438677Z",
      "message": "Building dependency tree...",
      "attributes": {
        "col": "30",
        "filename": "sdk/0.3.0/host.star",
        "line": "45",
        "thread": "up"
      },
      "stream": 0
    },
    {
      "timestamp": "2025-07-14T18:36:04.298471582Z",
      "message": "",
      "attributes": {
        "col": "30",
        "filename": "sdk/0.3.0/host.star",
        "line": "45",
        "thread": "up"
      },
      "stream": 0
    },
    {
      "timestamp": "2025-07-14T18:36:04.29850266Z",
      "message": "Reading state information...",
      "attributes": {
        "col": "30",
        "filename": "sdk/0.3.0/host.star",
        "line": "45",
        "thread": "up"
      },
      "stream": 0
    },
    {
      "timestamp": "2025-07-14T18:36:04.299309468Z",
      "message": "",
      "attributes": {
        "col": "30",
        "filename": "sdk/0.3.0/host.star",
        "line": "45",
        "thread": "up"
      },
      "stream": 0
    },
    {
      "timestamp": "2025-07-14T18:36:04.457590886Z",
      "message": "The following NEW packages will be installed:",
      "attributes": {
        "col": "30",
        "filename": "sdk/0.3.0/host.star",
        "line": "45",
        "thread": "up"
      },
      "stream": 0
    },
    {
      "timestamp": "2025-07-14T18:36:04.458212847Z",
      "message": "  infisical",
      "attributes": {
        "col": "30",
        "filename": "sdk/0.3.0/host.star",
        "line": "45",
        "thread": "up"
      },
      "stream": 0
    },
    {
      "timestamp": "2025-07-14T18:36:05.0074406Z",
      "message": "0 upgraded, 1 newly installed, 0 to remove and 22 not upgraded.",
      "attributes": {
        "col": "30",
        "filename": "sdk/0.3.0/host.star",
        "line": "45",
        "thread": "up"
      },
      "stream": 0
    },
    {
      "timestamp": "2025-07-14T18:36:05.00747244Z",
      "message": "Need to get 18.9 MB of archives.",
      "attributes": {
        "col": "30",
        "filename": "sdk/0.3.0/host.star",
        "line": "45",
        "thread": "up"
      },
      "stream": 0
    },
    {
      "timestamp": "2025-07-14T18:36:05.007479093Z",
      "message": "After this operation, 37.4 MB of additional disk space will be used.",
      "attributes": {
        "col": "30",
        "filename": "sdk/0.3.0/host.star",
        "line": "45",
        "thread": "up"
      },
      "stream": 0
    },
    {
      "timestamp": "2025-07-14T18:36:05.007484052Z",
      "message": "Get:1 https://dl.cloudsmith.io/public/infisical/infisical-cli/deb/ubuntu noble/main amd64 infisical amd64 0.38.0 [18.9 MB]",
      "attributes": {
        "col": "30",
        "filename": "sdk/0.3.0/host.star",
        "line": "45",
        "thread": "up"
      },
      "stream": 0
    },
    {
      "timestamp": "2025-07-14T18:36:05.3577181Z",
      "message": "Fetched 18.9 MB in 1s (29.2 MB/s)",
      "attributes": {
        "col": "30",
        "filename": "sdk/0.3.0/host.star",
        "line": "45",
        "thread": "up"
      },
      "stream": 0
    },
    {
      "timestamp": "2025-07-14T18:36:05.381831281Z",
      "message": "Selecting previously unselected package infisical.\r",
      "attributes": {
        "col": "30",
        "filename": "sdk/0.3.0/host.star",
        "line": "45",
        "thread": "up"
      },
      "stream": 0
    },
    {
      "timestamp": "2025-07-14T18:36:05.381850397Z",
      "message": "(Reading database ... \r",
      "attributes": {
        "col": "30",
        "filename": "sdk/0.3.0/host.star",
        "line": "45",
        "thread": "up"
      },
      "stream": 0
    },
    {
      "timestamp": "2025-07-14T18:36:05.40571477Z",
      "message": "(Reading database ... 5%\r(Reading database ... 10%\r(Reading database ... 15%\r(Reading database ... 20%\r(Reading database ... 25%\r(Reading database ... 30%\r",
      "attributes": {
        "col": "30",
        "filename": "sdk/0.3.0/host.star",
        "line": "45",
        "thread": "up"
      },
      "stream": 0
    },
    {
      "timestamp": "2025-07-14T18:36:05.405733806Z",
      "message": "(Reading database ... 35%\r(Reading database ... 40%\r(Reading database ... 45%",
      "attributes": {
        "col": "30",
        "filename": "sdk/0.3.0/host.star",
        "line": "45",
        "thread": "up"
      },
      "stream": 0
    },
    {
      "timestamp": "2025-07-14T18:36:05.405748914Z",
      "message": "\r(Reading database ... 50%\r",
      "attributes": {
        "col": "30",
        "filename": "sdk/0.3.0/host.star",
        "line": "45",
        "thread": "up"
      },
      "stream": 0
    },
    {
      "timestamp": "2025-07-14T18:36:05.405806445Z",
      "message": "(Reading database ... 55%\r",
      "attributes": {
        "col": "30",
        "filename": "sdk/0.3.0/host.star",
        "line": "45",
        "thread": "up"
      },
      "stream": 0
    },
    {
      "timestamp": "2025-07-14T18:36:05.414179433Z",
      "message": "(Reading database ... 60%\r",
      "attributes": {
        "col": "30",
        "filename": "sdk/0.3.0/host.star",
        "line": "45",
        "thread": "up"
      },
      "stream": 0
    },
    {
      "timestamp": "2025-07-14T18:36:05.442513079Z",
      "message": "(Reading database ... 65%\r",
      "attributes": {
        "col": "30",
        "filename": "sdk/0.3.0/host.star",
        "line": "45",
        "thread": "up"
      },
      "stream": 0
    },
    {
      "timestamp": "2025-07-14T18:36:05.4669123Z",
      "message": "(Reading database ... 70%\r",
      "attributes": {
        "col": "30",
        "filename": "sdk/0.3.0/host.star",
        "line": "45",
        "thread": "up"
      },
      "stream": 0
    },
    {
      "timestamp": "2025-07-14T18:36:05.501246046Z",
      "message": "(Reading database ... 75%\r",
      "attributes": {
        "col": "30",
        "filename": "sdk/0.3.0/host.star",
        "line": "45",
        "thread": "up"
      },
      "stream": 0
    },
    {
      "timestamp": "2025-07-14T18:36:05.522938245Z",
      "message": "(Reading database ... 80%\r",
      "attributes": {
        "col": "30",
        "filename": "sdk/0.3.0/host.star",
        "line": "45",
        "thread": "up"
      },
      "stream": 0
    },
    {
      "timestamp": "2025-07-14T18:36:05.545010999Z",
      "message": "(Reading database ... 85%\r",
      "attributes": {
        "col": "30",
        "filename": "sdk/0.3.0/host.star",
        "line": "45",
        "thread": "up"
      },
      "stream": 0
    },
    {
      "timestamp": "2025-07-14T18:36:05.570993761Z",
      "message": "(Reading database ... 90%\r",
      "attributes": {
        "col": "30",
        "filename": "sdk/0.3.0/host.star",
        "line": "45",
        "thread": "up"
      },
      "stream": 0
    },
    {
      "timestamp": "2025-07-14T18:36:05.63876732Z",
      "message": "(Reading database ... 95%\r",
      "attributes": {
        "col": "30",
        "filename": "sdk/0.3.0/host.star",
        "line": "45",
        "thread": "up"
      },
      "stream": 0
    },
    {
      "timestamp": "2025-07-14T18:36:05.659127622Z",
      "message": "(Reading database ... 100%\r(Reading database ... 219506 files and directories currently installed.)\r",
      "attributes": {
        "col": "30",
        "filename": "sdk/0.3.0/host.star",
        "line": "45",
        "thread": "up"
      },
      "stream": 0
    },
    {
      "timestamp": "2025-07-14T18:36:05.663344297Z",
      "message": "Preparing to unpack .../infisical_0.38.0_amd64.deb ...\r",
      "attributes": {
        "col": "30",
        "filename": "sdk/0.3.0/host.star",
        "line": "45",
        "thread": "up"
      },
      "stream": 0
    },
    {
      "timestamp": "2025-07-14T18:36:05.666258771Z",
      "message": "Unpacking infisical (0.38.0) ...\r",
      "attributes": {
        "col": "30",
        "filename": "sdk/0.3.0/host.star",
        "line": "45",
        "thread": "up"
      },
      "stream": 0
    },
    {
      "timestamp": "2025-07-14T18:36:05.908098558Z",
      "message": "Setting up infisical (0.38.0) ...\r",
      "attributes": {
        "col": "30",
        "filename": "sdk/0.3.0/host.star",
        "line": "45",
        "thread": "up"
      },
      "stream": 0
    },
    {
      "timestamp": "2025-07-14T18:36:05.912142628Z",
      "message": "Processing triggers for man-db (2.12.0-4build2) ...\r",
      "attributes": {
        "col": "30",
        "filename": "sdk/0.3.0/host.star",
        "line": "45",
        "thread": "up"
      },
      "stream": 0
    },
    {
      "timestamp": "2025-07-14T18:36:13.716360838Z",
      "message": "",
      "attributes": {
        "col": "30",
        "filename": "sdk/0.3.0/host.star",
        "line": "45",
        "thread": "up"
      },
      "stream": 0
    },
    {
      "timestamp": "2025-07-14T18:36:13.716384934Z",
      "message": "Running kernel seems to be up-to-date.",
      "attributes": {
        "col": "30",
        "filename": "sdk/0.3.0/host.star",
        "line": "45",
        "thread": "up"
      },
      "stream": 0
    },
    {
      "timestamp": "2025-07-14T18:36:13.716391706Z",
      "message": "Restarting services...",
      "attributes": {
        "col": "30",
        "filename": "sdk/0.3.0/host.star",
        "line": "45",
        "thread": "up"
      },
      "stream": 0
    },
    {
      "timestamp": "2025-07-14T18:36:13.723565517Z",
      "message": "",
      "attributes": {
        "col": "30",
        "filename": "sdk/0.3.0/host.star",
        "line": "45",
        "thread": "up"
      },
      "stream": 0
    },
    {
      "timestamp": "2025-07-14T18:36:13.723622376Z",
      "message": "Service restarts being deferred:",
      "attributes": {
        "col": "30",
        "filename": "sdk/0.3.0/host.star",
        "line": "45",
        "thread": "up"
      },
      "stream": 0
    },
    {
      "timestamp": "2025-07-14T18:36:13.723859721Z",
      "message": " systemctl restart hosted-compute-agent.service",
      "attributes": {
        "col": "30",
        "filename": "sdk/0.3.0/host.star",
        "line": "45",
        "thread": "up"
      },
      "stream": 0
    },
    {
      "timestamp": "2025-07-14T18:36:13.723936873Z",
      "message": "No containers need to be restarted.",
      "attributes": {
        "col": "30",
        "filename": "sdk/0.3.0/host.star",
        "line": "45",
        "thread": "up"
      },
      "stream": 0
    },
    {
      "timestamp": "2025-07-14T18:36:13.723947323Z",
      "message": "No user sessions are running outdated binaries.",
      "attributes": {
        "col": "30",
        "filename": "sdk/0.3.0/host.star",
        "line": "45",
        "thread": "up"
      },
      "stream": 0
    },
    {
      "timestamp": "2025-07-14T18:36:13.723981126Z",
      "message": "No VM guests are running outdated hypervisor (qemu) binaries on this host.",
      "attributes": {
        "col": "30",
        "filename": "sdk/0.3.0/host.star",
        "line": "45",
        "thread": "up"
      },
      "stream": 0
    },
    {
      "timestamp": "2025-07-14T18:36:14.543325802Z",
      "message": "Logging in with credentials in INFISICAL_CLIENT_ID and INFISICAL_CLIENT_SECRET",
      "attributes": {
        "col": "14",
        "filename": "../infisical.star",
        "line": "46",
        "thread": "up"
      },
      "stream": 0
    },
    {
      "timestamp": "2025-07-14T18:36:14.825749617Z",
      "message": "Retrieving kubeconfig from Infisical using key K8S_DEMO_KUBECONFIG",
      "attributes": {
        "col": "10",
        "filename": "./tasks.ocu.star",
        "line": "30",
        "thread": "up"
      },
      "stream": 0
    },
    {
      "timestamp": "2025-07-14T18:36:15.010025453Z",
      "message": "Successfully retrieved kubeconfig",
      "attributes": {
        "col": "10",
        "filename": "./tasks.ocu.star",
        "line": "36",
        "thread": "up"
      },
      "stream": 0
    },
    {
      "timestamp": "2025-07-14T18:36:15.011561446Z",
      "message": "/usr/local/bin/helm",
      "attributes": {
        "col": "30",
        "filename": "sdk/0.3.0/host.star",
        "line": "45",
        "thread": "up"
      },
      "stream": 0
    },
    {
      "timestamp": "2025-07-14T18:36:15.017299193Z",
      "message": "/usr/bin/kubectl",
      "attributes": {
        "col": "30",
        "filename": "sdk/0.3.0/host.star",
        "line": "45",
        "thread": "up"
      },
      "stream": 0
    },
    {
      "timestamp": "2025-07-14T18:36:15.019175563Z",
      "message": "Testing cluster connectivity...",
      "attributes": {
        "col": "10",
        "filename": "./tasks.ocu.star",
        "line": "45",
        "thread": "up"
      },
      "stream": 0
    },
    {
      "timestamp": "2025-07-14T18:36:18.150461473Z",
      "message": "Client Version: v1.33.2",
      "attributes": {
        "col": "30",
        "filename": "sdk/0.3.0/host.star",
        "line": "45",
        "thread": "up"
      },
      "stream": 0
    },
    {
      "timestamp": "2025-07-14T18:36:18.150488614Z",
      "message": "Kustomize Version: v5.6.0",
      "attributes": {
        "col": "30",
        "filename": "sdk/0.3.0/host.star",
        "line": "45",
        "thread": "up"
      },
      "stream": 0
    },
    {
      "timestamp": "2025-07-14T18:36:18.150492982Z",
      "message": "Server Version: v1.31.9",
      "attributes": {
        "col": "30",
        "filename": "sdk/0.3.0/host.star",
        "line": "45",
        "thread": "up"
      },
      "stream": 0
    },
    {
      "timestamp": "2025-07-14T18:36:18.15051333Z",
      "message": "WARNING: version difference between client (1.33) and server (1.31) exceeds the supported minor version skew of +/-1",
      "attributes": {
        "col": "30",
        "filename": "sdk/0.3.0/host.star",
        "line": "45",
        "thread": "up"
      },
      "stream": 0
    },
    {
      "timestamp": "2025-07-14T18:36:18.153018564Z",
      "message": "Creating namespace if it doesn't exist...",
      "attributes": {
        "col": "10",
        "filename": "./tasks.ocu.star",
        "line": "52",
        "thread": "up"
      },
      "stream": 0
    },
    {
      "timestamp": "2025-07-14T18:36:18.487753731Z",
      "message": "namespace/nginx configured",
      "attributes": {
        "col": "30",
        "filename": "sdk/0.3.0/host.star",
        "line": "45",
        "thread": "up"
      },
      "stream": 0
    },
    {
      "timestamp": "2025-07-14T18:36:18.490376652Z",
      "message": "Adding bitnami Helm repository...",
      "attributes": {
        "col": "10",
        "filename": "./tasks.ocu.star",
        "line": "59",
        "thread": "up"
      },
      "stream": 0
    },
    {
      "timestamp": "2025-07-14T18:36:23.717914063Z",
      "message": "\"bitnami\" has been added to your repositories",
      "attributes": {
        "col": "30",
        "filename": "sdk/0.3.0/host.star",
        "line": "45",
        "thread": "up"
      },
      "stream": 0
    },
    {
      "timestamp": "2025-07-14T18:36:23.772988647Z",
      "message": "Hang tight while we grab the latest from your chart repositories...",
      "attributes": {
        "col": "30",
        "filename": "sdk/0.3.0/host.star",
        "line": "45",
        "thread": "up"
      },
      "stream": 0
    },
    {
      "timestamp": "2025-07-14T18:36:26.100038997Z",
      "message": "...Successfully got an update from the \"bitnami\" chart repository",
      "attributes": {
        "col": "30",
        "filename": "sdk/0.3.0/host.star",
        "line": "45",
        "thread": "up"
      },
      "stream": 0
    },
    {
      "timestamp": "2025-07-14T18:36:26.100065677Z",
      "message": "Update Complete. ⎈Happy Helming!⎈",
      "attributes": {
        "col": "30",
        "filename": "sdk/0.3.0/host.star",
        "line": "45",
        "thread": "up"
      },
      "stream": 0
    },
    {
      "timestamp": "2025-07-14T18:36:26.105070664Z",
      "message": "Updating Helm chart dependencies...",
      "attributes": {
        "col": "10",
        "filename": "./tasks.ocu.star",
        "line": "67",
        "thread": "up"
      },
      "stream": 0
    },
    {
      "timestamp": "2025-07-14T18:36:26.162963603Z",
      "message": "Hang tight while we grab the latest from your chart repositories...",
      "attributes": {
        "col": "30",
        "filename": "sdk/0.3.0/host.star",
        "line": "45",
        "thread": "up"
      },
      "stream": 0
    },
    {
      "timestamp": "2025-07-14T18:36:28.739823056Z",
      "message": "...Successfully got an update from the \"bitnami\" chart repository",
      "attributes": {
        "col": "30",
        "filename": "sdk/0.3.0/host.star",
        "line": "45",
        "thread": "up"
      },
      "stream": 0
    },
    {
      "timestamp": "2025-07-14T18:36:28.739846821Z",
      "message": "Update Complete. ⎈Happy Helming!⎈",
      "attributes": {
        "col": "30",
        "filename": "sdk/0.3.0/host.star",
        "line": "45",
        "thread": "up"
      },
      "stream": 0
    },
    {
      "timestamp": "2025-07-14T18:36:32.872415822Z",
      "message": "Saving 1 charts",
      "attributes": {
        "col": "30",
        "filename": "sdk/0.3.0/host.star",
        "line": "45",
        "thread": "up"
      },
      "stream": 0
    },
    {
      "timestamp": "2025-07-14T18:36:32.872544992Z",
      "message": "Downloading nginx from repo https://charts.bitnami.com/bitnami",
      "attributes": {
        "col": "30",
        "filename": "sdk/0.3.0/host.star",
        "line": "45",
        "thread": "up"
      },
      "stream": 0
    },
    {
      "timestamp": "2025-07-14T18:36:35.053266516Z",
      "message": "Deleting outdated charts",
      "attributes": {
        "col": "30",
        "filename": "sdk/0.3.0/host.star",
        "line": "45",
        "thread": "up"
      },
      "stream": 0
    },
    {
      "timestamp": "2025-07-14T18:36:35.064450773Z",
      "message": "Installing nginx via custom Helm chart in staging environment...",
      "attributes": {
        "col": "10",
        "filename": "./tasks.ocu.star",
        "line": "74",
        "thread": "up"
      },
      "stream": 0
    },
    {
      "timestamp": "2025-07-14T18:36:36.598363539Z",
      "message": "Release \"nginx-custom\" has been upgraded. Happy Helming!",
      "attributes": {
        "col": "30",
        "filename": "sdk/0.3.0/host.star",
        "line": "45",
        "thread": "up"
      },
      "stream": 0
    },
    {
      "timestamp": "2025-07-14T18:36:36.59839097Z",
      "message": "NAME: nginx-custom",
      "attributes": {
        "col": "30",
        "filename": "sdk/0.3.0/host.star",
        "line": "45",
        "thread": "up"
      },
      "stream": 0
    },
    {
      "timestamp": "2025-07-14T18:36:36.598395288Z",
      "message": "LAST DEPLOYED: Mon Jul 14 18:36:35 2025",
      "attributes": {
        "col": "30",
        "filename": "sdk/0.3.0/host.star",
        "line": "45",
        "thread": "up"
      },
      "stream": 0
    },
    {
      "timestamp": "2025-07-14T18:36:36.598405838Z",
      "message": "NAMESPACE: nginx",
      "attributes": {
        "col": "30",
        "filename": "sdk/0.3.0/host.star",
        "line": "45",
        "thread": "up"
      },
      "stream": 0
    },
    {
      "timestamp": "2025-07-14T18:36:36.598410266Z",
      "message": "STATUS: deployed",
      "attributes": {
        "col": "30",
        "filename": "sdk/0.3.0/host.star",
        "line": "45",
        "thread": "up"
      },
      "stream": 0
    },
    {
      "timestamp": "2025-07-14T18:36:36.598413533Z",
      "message": "REVISION: 7",
      "attributes": {
        "col": "30",
        "filename": "sdk/0.3.0/host.star",
        "line": "45",
        "thread": "up"
      },
      "stream": 0
    },
    {
      "timestamp": "2025-07-14T18:36:36.59841739Z",
      "message": "TEST SUITE: None",
      "attributes": {
        "col": "30",
        "filename": "sdk/0.3.0/host.star",
        "line": "45",
        "thread": "up"
      },
      "stream": 0
    },
    {
      "timestamp": "2025-07-14T18:36:36.601208753Z",
      "message": "Finding nginx service...",
      "attributes": {
        "col": "10",
        "filename": "./tasks.ocu.star",
        "line": "99",
        "thread": "up"
      },
      "stream": 0
    },
    {
      "timestamp": "2025-07-14T18:36:36.709442615Z",
      "message": "nginx-custom",
      "attributes": {
        "col": "30",
        "filename": "sdk/0.3.0/host.star",
        "line": "45",
        "thread": "up"
      },
      "stream": 0
    },
    {
      "timestamp": "2025-07-14T18:36:36.712068783Z",
      "message": "Found nginx service: nginx-custom",
      "attributes": {
        "col": "10",
        "filename": "./tasks.ocu.star",
        "line": "115",
        "thread": "up"
      },
      "stream": 0
    },
    {
      "timestamp": "2025-07-14T18:36:36.712084482Z",
      "message": "Waiting for nginx pods to be ready...",
      "attributes": {
        "col": "10",
        "filename": "./tasks.ocu.star",
        "line": "118",
        "thread": "up"
      },
      "stream": 0
    },
    {
      "timestamp": "2025-07-14T18:36:36.930952833Z",
      "message": "pod/nginx-custom-86c6764d9d-l7mh7 condition met",
      "attributes": {
        "col": "30",
        "filename": "sdk/0.3.0/host.star",
        "line": "45",
        "thread": "up"
      },
      "stream": 0
    },
    {
      "timestamp": "2025-07-14T18:36:36.933852548Z",
      "message": "Checking for LoadBalancer IP assignment...",
      "attributes": {
        "col": "10",
        "filename": "./tasks.ocu.star",
        "line": "126",
        "thread": "up"
      },
      "stream": 0
    },
    {
      "timestamp": "2025-07-14T18:36:37.042166199Z",
      "message": "157.230.65.184",
      "attributes": {
        "col": "30",
        "filename": "sdk/0.3.0/host.star",
        "line": "45",
        "thread": "up"
      },
      "stream": 0
    },
    {
      "timestamp": "2025-07-14T18:36:37.044639287Z",
      "message": "Getting LoadBalancer IP...",
      "attributes": {
        "col": "10",
        "filename": "./tasks.ocu.star",
        "line": "138",
        "thread": "up"
      },
      "stream": 0
    },
    {
      "timestamp": "2025-07-14T18:36:37.120715445Z",
      "message": "157.230.65.184",
      "attributes": {
        "col": "30",
        "filename": "sdk/0.3.0/host.star",
        "line": "45",
        "thread": "up"
      },
      "stream": 0
    },
    {
      "timestamp": "2025-07-14T18:36:37.22839853Z",
      "message": "Nginx deployment completed in staging environment.",
      "attributes": {
        "col": "10",
        "filename": "./tasks.ocu.star",
        "line": "168",
        "thread": "up"
      },
      "stream": 0
    },
    {
      "timestamp": "2025-07-14T18:36:37.228420541Z",
      "message": "Access the service at: http://157.230.65.184",
      "attributes": {
        "col": "14",
        "filename": "./tasks.ocu.star",
        "line": "170",
        "thread": "up"
      },
      "stream": 0
    }
  ]
}